pcwawc/__init__.py
pcwawc/args.py
pcwawc/board.py
pcwawc/boarddetector.py
pcwawc/boardfinder.py
pcwawc/chessengine.py
pcwawc/chessimage.py
pcwawc/chesstrapezoid.py
pcwawc/chessvision.py
pcwawc/ciede2000.py
pcwawc/config.py
pcwawc/detectorfactory.py
pcwawc/detectstate.py
pcwawc/environment.py
pcwawc/environment4test.py
pcwawc/eventhandling.py
pcwawc/field.py
pcwawc/fpscheck.py
pcwawc/game.py
pcwawc/histogram.py
pcwawc/jsonablemixin.py
pcwawc/lichessbridge.py
pcwawc/plotlib.py
pcwawc/runningstats.py
pcwawc/simpledetector.py
pcwawc/video.py
pcwawc/videoanalyze.py
pcwawc/webapp.py
pcwawc/webchesscam.py
pcwawc/yamlablemixin.py
pcwawc/imutils/__init__.py
pcwawc/imutils/perspective.py
pcwawc/templates/footer.html
pcwawc/templates/header.html
pcwawc/templates/index.html
pcwawc/templates/js.html
pcwawc/templates/menu.html
play_chess_with_a_webcam-0.0.2.dist-info/METADATA
play_chess_with_a_webcam-0.0.2.dist-info/WHEEL
play_chess_with_a_webcam-0.0.2.dist-info/entry_points.txt
play_chess_with_a_webcam-0.0.2.dist-info/licenses/LICENSE
play_chess_with_a_webcam-0.0.2.dist-info/RECORD
