Metadata-Version: 2.4
Name: play-chess-with-a-webcam
Version: 0.0.2
Summary: Play chess with a webcam
Project-URL: Home, https://github.com/WolfgangFahl/play-chess-with-a-webcam
Project-URL: Documentation, https://wiki.bitplan.com/index.php/Play-chess-with-a-webcam
Project-URL: Source, https://github.com/WolfgangFahl/play-chess-with-a-webcam
Author-email: Wolfgang Fahl <wf@bitplan.com>
Maintainer-email: Wolfgang Fahl <wf@bitplan.com>
License-Expression: Apache-2.0
License-File: LICENSE
Keywords: chess,computer vision,lichess,webcam
Classifier: Development Status :: 4 - Beta
Classifier: Environment :: Web Environment
Classifier: Intended Audience :: Developers
Classifier: Intended Audience :: Education
Classifier: Intended Audience :: Science/Research
Classifier: License :: OSI Approved :: Apache Software License
Classifier: Operating System :: OS Independent
Classifier: Programming Language :: Python :: 3 :: Only
Classifier: Programming Language :: Python :: 3.9
Classifier: Programming Language :: Python :: 3.10
Classifier: Programming Language :: Python :: 3.11
Classifier: Programming Language :: Python :: 3.12
Classifier: Programming Language :: Python :: 3.13
Classifier: Topic :: Software Development :: Libraries :: Python Modules
Requires-Python: >=3.9
Requires-Dist: berserk==0.3.1
Requires-Dist: flask-autoindex==0.6.6
Requires-Dist: flask-restful==0.3.10
Requires-Dist: flask==2.3.2
Requires-Dist: imutils==0.5.3
Requires-Dist: interface==2.11.1
Requires-Dist: jsonpickle==1.2
Requires-Dist: mss==4.0.3
Requires-Dist: opencv-python==4.10.0.84
Requires-Dist: pillow==9.3.0
Requires-Dist: python-chess==0.30.0
Requires-Dist: python-lichess==0.9
Requires-Dist: pyyaml>=6.0.2
Provides-Extra: test
Requires-Dist: matplotlib>=3.10.1; extra == 'test'
Requires-Dist: pytest-cov>=6.0.0; extra == 'test'
Requires-Dist: pytest>=8.3.5; extra == 'test'
Requires-Dist: scipy>=1.15.2; extra == 'test'
